Workbook

Sheet Read Me
A1: 3-Statement Financial Model Template
A2: Income Statement + Balance Sheet + Cash Flow Statement — fully linked, editable
A4: How this workbook is built
A5: Color code
A6: Blue text on yellow fill | B6: A hardcoded input. Type over these numbers with your own figures.
A7: Black text | B7: A formula. Do not overwrite — it recalculates automatically from inputs above/around it.
A8: Green text | B8: A live link pulling a number from another sheet (e.g. Net Income flowing from the Income Statement into the Balance Sheet and Cash Flow Statement).
A9: Red bold text | B9: A balance check. Should always read 0. If it doesn't, an input was changed in a way that breaks the link between statements.
A11: How the three statements connect
A12: Income Statement -> Balance Sheet | B12: Net Income flows into Retained Earnings; Depreciation & Amortization flows into Cash Flow.
A13: Income Statement -> Cash Flow | B13: Net Income is the starting line of Cash Flow from Operations; D&A is added back.
A14: Balance Sheet -> Cash Flow | B14: Year-over-year changes in Accounts Receivable, Inventory, Prepaid Expenses, Accounts Payable and Accrued Liabilities drive the working-capital lines.
A15: Cash Flow -> Balance Sheet | B15: Ending Cash Balance on the Cash Flow Statement is linked into the Cash line on the Balance Sheet.
A17: To edit
A18: Change any blue input | B18: e.g. Sales Revenue, COGS, tax rate, Accounts Receivable, Capital Expenditures — every formula downstream recalculates automatically.
A19: Add a period | B19: Insert a column, copy the formulas from the adjacent period column across, and update any year-over-year references.
A20: Rename line items | B20: Just overwrite the label in column A; formulas reference cell addresses, not text, so this is safe.
A22: Notes / assumptions used in this template
A23: Year 1 working-capital changes | B23: Set to 0 in the Cash Flow Statement because there is no prior-period Balance Sheet to compare against. Once you add real historical data, replace with the actual change.
A24: Tax | B24: Calculated as Income Before Tax x an editable Tax Rate assumption, not a hardcoded tax expense.
A25: PP&E, Debt, Common Stock, Retained Earnings | B25: Roll forward automatically: Gross PP&E moves with Capex, Accumulated Depreciation with D&A, Long-term Debt with Debt Issued/(Repaid), Common Stock with Equity Issued, and Retained Earnings with Net Income and Dividends. Edit the Cash Flow Statement inputs, not these Balance Sheet cells, to change them.
A26: Other Investing Activities | B26: Left at 0 by default because it has no matching Balance Sheet line in this template. If you use it, also adjust a Balance Sheet asset so the Balance Check stays at zero.
A27: All figures | B27: Are illustrative placeholders — replace every yellow-highlighted cell with your own numbers before relying on this model.
A29: Ratio Analysis tab
A30: What it does | B30: Evaluates all three statements together: profitability, liquidity, leverage, efficiency and cash flow ratios, each computed live from the Income Statement, Balance Sheet and Cash Flow Statement. Nothing to edit here — every cell is a green cross-sheet formula that updates automatically as you change inputs elsewhere.

Sheet Income Statement
A1: Income Statement
A2: ($ in thousands) — edit blue/yellow cells; all totals are formulas
B4: Year 1 | C4: Year 2 | D4: Year 3
A6: Revenue
A7: Sales Revenue | B7: 10000 | C7: 10000 | D7: 10000
A8: Other Revenue | B8: 250 | C8: 250 | D8: 250
A9: Total Revenue | B9: =SUM(B7:B8) -> 10250 | C9: =SUM(C7:C8) -> 10250 | D9: =SUM(D7:D8) -> 10250
A11: Cost of Goods Sold | B11: 4200 | C11: 4200 | D11: 4200
A12: Gross Profit | B12: =B9-B11 -> 6050 | C12: =C9-C11 -> 6050 | D12: =D9-D11 -> 6050
A14: Operating Expenses
A15: Salaries & Wages | B15: 2800 | C15: 2800 | D15: 2800
A16: Rent | B16: 600 | C16: 600 | D16: 600
A17: Marketing | B17: 450 | C17: 450 | D17: 450
A18: Utilities | B18: 180 | C18: 180 | D18: 180
A19: Depreciation & Amortization | B19: 350 | C19: 350 | D19: 350
A20: Other Operating Expenses | B20: 320 | C20: 320 | D20: 320
A21: Total Operating Expenses | B21: =SUM(B15:B20) -> 4700 | C21: =SUM(C15:C20) -> 4700 | D21: =SUM(D15:D20) -> 4700
A23: Operating Income (EBIT) | B23: =B12-B21 -> 1350 | C23: =C12-C21 -> 1350 | D23: =D12-D21 -> 1350
A25: Other Income (Expense)
A26: Interest Expense | B26: -150 | C26: -150 | D26: -150
A27: Interest Income | B27: 20 | C27: 20 | D27: 20
A28: Total Other Income (Expense) | B28: =SUM(B26:B27) -> -130 | C28: =SUM(C26:C27) -> -130 | D28: =SUM(D26:D27) -> -130
A30: Income Before Tax | B30: =B23+B28 -> 1220 | C30: =C23+C28 -> 1220 | D30: =D23+D28 -> 1220
A31: Tax Rate (assumption) | B31: 0.21 | C31: 0.21 | D31: 0.21
A32: Income Tax Expense | B32: =B30*B31 -> 256.2 | C32: =C30*C31 -> 256.2 | D32: =D30*D31 -> 256.2
A34: NET INCOME | B34: =B30-B32 -> 963.8 | C34: =C30-C32 -> 963.8 | D34: =D30-D32 -> 963.8

Sheet Balance Sheet
A1: Balance Sheet
A2: ($ in thousands) — Cash links from Cash Flow Statement; Retained Earnings links from Income Statement
B4: ='Income Statement'!B4 -> Year 1 | C4: ='Income Statement'!C4 -> Year 2 | D4: ='Income Statement'!D4 -> Year 3
A6: ASSETS
A7: Current Assets
A8: Cash & Cash Equivalents | B8: ='Cash Flow Statement'!B29 -> 1113.8 | C8: ='Cash Flow Statement'!C29 -> 1427.6 | D8: ='Cash Flow Statement'!D29 -> 1741.4
A9: Accounts Receivable | B9: 1400 | C9: 1400 | D9: 1400
A10: Inventory | B10: 1100 | C10: 1100 | D10: 1100
A11: Prepaid Expenses | B11: 150 | C11: 150 | D11: 150
A12: Other Current Assets | B12: 200 | C12: 200 | D12: 200
A13: Total Current Assets | B13: =SUM(B8:B12) -> 3963.8 | C13: =SUM(C8:C12) -> 4277.6 | D13: =SUM(D8:D12) -> 4591.4
A15: Non-Current Assets
A16: Property, Plant & Equipment (gross) | B16: 6000 | C16: =B16-'Cash Flow Statement'!C17 -> 6500 | D16: =C16-'Cash Flow Statement'!D17 -> 7000
A17: Less: Accumulated Depreciation | B17: -1200 | C17: =B17-'Income Statement'!C19 -> -1550 | D17: =C17-'Income Statement'!D19 -> -1900
A18: Net PP&E | B18: =B16+B17 -> 4800 | C18: =C16+C17 -> 4950 | D18: =D16+D17 -> 5100
A19: Intangible Assets | B19: 500 | C19: 500 | D19: 500
A20: Other Long-term Assets | B20: 100 | C20: 100 | D20: 100
A21: Total Non-Current Assets | B21: =B18+B19+B20 -> 5400 | C21: =C18+C19+C20 -> 5550 | D21: =D18+D19+D20 -> 5700
A23: TOTAL ASSETS | B23: =B13+B21 -> 9363.8 | C23: =C13+C21 -> 9827.6 | D23: =D13+D21 -> 10291.4
A25: LIABILITIES
A26: Current Liabilities
A27: Accounts Payable | B27: 900 | C27: 900 | D27: 900
A28: Accrued Liabilities | B28: 350 | C28: 350 | D28: 350
A29: Short-term Debt | B29: 500 | C29: 500 | D29: 500
A30: Other Current Liabilities | B30: 150 | C30: 150 | D30: 150
A31: Total Current Liabilities | B31: =SUM(B27:B30) -> 1900 | C31: =SUM(C27:C30) -> 1900 | D31: =SUM(D27:D30) -> 1900
A33: Long-term Liabilities
A34: Long-term Debt | B34: 2500 | C34: =B34+'Cash Flow Statement'!C22 -> 2300 | D34: =C34+'Cash Flow Statement'!D22 -> 2100
A35: Other Long-term Liabilities | B35: 200 | C35: 200 | D35: 200
A36: Total Long-term Liabilities | B36: =SUM(B34:B35) -> 2700 | C36: =SUM(C34:C35) -> 2500 | D36: =SUM(D34:D35) -> 2300
A38: Total Liabilities | B38: =B31+B36 -> 4600 | C38: =C31+C36 -> 4400 | D38: =D31+D36 -> 4200
A40: EQUITY
A41: Common Stock | B41: 3000 | C41: =B41+'Cash Flow Statement'!C23 -> 3000 | D41: =C41+'Cash Flow Statement'!D23 -> 3000
A42: Retained Earnings | B42: 1763.8 | C42: =B42+'Income Statement'!C34+'Cash Flow Statement'!C24 -> 2427.6 | D42: =C42+'Income Statement'!D34+'Cash Flow Statement'!D24 -> 3091.4
A43: Total Equity | B43: =B41+B42 -> 4763.8 | C43: =C41+C42 -> 5427.6 | D43: =D41+D42 -> 6091.4
A45: TOTAL LIABILITIES & EQUITY | B45: =B38+B43 -> 9363.8 | C45: =C38+C43 -> 9827.6 | D45: =D38+D43 -> 10291.4
A47: Balance Check (Assets - Liab&Equity, should = 0) | B47: =B23-B45 -> 0 | C47: =C23-C45 -> 0 | D47: =D23-D45 -> 0

Sheet Cash Flow Statement
A1: Cash Flow Statement
A2: ($ in thousands) — Indirect method, fully linked to Income Statement and Balance Sheet
B4: ='Income Statement'!B4 -> Year 1 | C4: ='Income Statement'!C4 -> Year 2 | D4: ='Income Statement'!D4 -> Year 3
A6: Cash Flow from Operating Activities
A7: Net Income | B7: ='Income Statement'!B34 -> 963.8 | C7: ='Income Statement'!C34 -> 963.8 | D7: ='Income Statement'!D34 -> 963.8
A8: Add: Depreciation & Amortization | B8: ='Income Statement'!B19 -> 350 | C8: ='Income Statement'!C19 -> 350 | D8: ='Income Statement'!D19 -> 350
A9: (Increase) / Decrease in Accounts Receivable | B9: 0 | C9: =-('Balance Sheet'!C9-'Balance Sheet'!B9) -> 0 | D9: =-('Balance Sheet'!D9-'Balance Sheet'!C9) -> 0
A10: (Increase) / Decrease in Inventory | B10: 0 | C10: =-('Balance Sheet'!C10-'Balance Sheet'!B10) -> 0 | D10: =-('Balance Sheet'!D10-'Balance Sheet'!C10) -> 0
A11: (Increase) / Decrease in Prepaid Expenses | B11: 0 | C11: =-('Balance Sheet'!C11-'Balance Sheet'!B11) -> 0 | D11: =-('Balance Sheet'!D11-'Balance Sheet'!C11) -> 0
A12: Increase / (Decrease) in Accounts Payable | B12: 0 | C12: ='Balance Sheet'!C27-'Balance Sheet'!B27 -> 0 | D12: ='Balance Sheet'!D27-'Balance Sheet'!C27 -> 0
A13: Increase / (Decrease) in Accrued Liabilities | B13: 0 | C13: ='Balance Sheet'!C28-'Balance Sheet'!B28 -> 0 | D13: ='Balance Sheet'!D28-'Balance Sheet'!C28 -> 0
A14: Net Cash from Operating Activities | B14: =SUM(B7:B13) -> 1313.8 | C14: =SUM(C7:C13) -> 1313.8 | D14: =SUM(D7:D13) -> 1313.8
A16: Cash Flow from Investing Activities
A17: Capital Expenditures | B17: -500 | C17: -500 | D17: -500
A18: Other Investing Activities | B18: 0 | C18: 0 | D18: 0
A19: Net Cash from Investing Activities | B19: =SUM(B17:B18) -> -500 | C19: =SUM(C17:C18) -> -500 | D19: =SUM(D17:D18) -> -500
A21: Cash Flow from Financing Activities
A22: Debt Issued / (Repaid) | B22: -200 | C22: -200 | D22: -200
A23: Equity Issued | B23: 0 | C23: 0 | D23: 0
A24: Dividends Paid | B24: -300 | C24: -300 | D24: -300
A25: Net Cash from Financing Activities | B25: =SUM(B22:B24) -> -500 | C25: =SUM(C22:C24) -> -500 | D25: =SUM(D22:D24) -> -500
A27: Net Increase / (Decrease) in Cash | B27: =B14+B19+B25 -> 313.8 | C27: =C14+C19+C25 -> 313.8 | D27: =D14+D19+D25 -> 313.8
A28: Beginning Cash Balance | B28: 800 | C28: =B29 -> 1113.8 | D28: =C29 -> 1427.6
A29: ENDING CASH BALANCE | B29: =B27+B28 -> 1113.8 | C29: =C27+C28 -> 1427.6 | D29: =D27+D28 -> 1741.4

Sheet Ratio Analysis
A1: Ratio Analysis
A2: Every cell here is a live formula pulling from the Income Statement, Balance Sheet and Cash Flow Statement
B4: ='Income Statement'!B4 -> Year 1 | C4: ='Income Statement'!C4 -> Year 2 | D4: ='Income Statement'!D4 -> Year 3
A6: Profitability Ratios
A7: Gross Profit Margin | B7: ='Income Statement'!B12/'Income Statement'!B9 -> 0.5902439 | C7: ='Income Statement'!C12/'Income Statement'!C9 -> 0.5902439 | D7: ='Income Statement'!D12/'Income Statement'!D9 -> 0.5902439
A8: Operating Margin (EBIT Margin) | B8: ='Income Statement'!B23/'Income Statement'!B9 -> 0.13170732 | C8: ='Income Statement'!C23/'Income Statement'!C9 -> 0.13170732 | D8: ='Income Statement'!D23/'Income Statement'!D9 -> 0.13170732
A9: Net Profit Margin | B9: ='Income Statement'!B34/'Income Statement'!B9 -> 0.094029268 | C9: ='Income Statement'!C34/'Income Statement'!C9 -> 0.094029268 | D9: ='Income Statement'!D34/'Income Statement'!D9 -> 0.094029268
A10: Return on Assets (ROA) | B10: ='Income Statement'!B34/'Balance Sheet'!B23 -> 0.1029283 | C10: ='Income Statement'!C34/'Balance Sheet'!C23 -> 0.09807074 | D10: ='Income Statement'!D34/'Balance Sheet'!D23 -> 0.09365101
A11: Return on Equity (ROE) | B11: ='Income Statement'!B34/'Balance Sheet'!B43 -> 0.20231748 | C11: ='Income Statement'!C34/'Balance Sheet'!C43 -> 0.17757388 | D11: ='Income Statement'!D34/'Balance Sheet'!D43 -> 0.15822307
A13: Liquidity Ratios
A14: Current Ratio | B14: ='Balance Sheet'!B13/'Balance Sheet'!B31 -> 2.0862105 | C14: ='Balance Sheet'!C13/'Balance Sheet'!C31 -> 2.2513684 | D14: ='Balance Sheet'!D13/'Balance Sheet'!D31 -> 2.4165263
A15: Quick Ratio | B15: =('Balance Sheet'!B13-'Balance Sheet'!B10)/'Balance Sheet'!B31 -> 1.5072632 | C15: =('Balance Sheet'!C13-'Balance Sheet'!C10)/'Balance Sheet'!C31 -> 1.6724211 | D15: =('Balance Sheet'!D13-'Balance Sheet'!D10)/'Balance Sheet'!D31 -> 1.8375789
A16: Working Capital ($) | B16: ='Balance Sheet'!B13-'Balance Sheet'!B31 -> 2063.8 | C16: ='Balance Sheet'!C13-'Balance Sheet'!C31 -> 2377.6 | D16: ='Balance Sheet'!D13-'Balance Sheet'!D31 -> 2691.4
A18: Leverage Ratios
A19: Debt-to-Equity | B19: =('Balance Sheet'!B29+'Balance Sheet'!B34)/'Balance Sheet'!B43 -> 0.62974936 | C19: =('Balance Sheet'!C29+'Balance Sheet'!C34)/'Balance Sheet'!C43 -> 0.51588179 | D19: =('Balance Sheet'!D29+'Balance Sheet'!D34)/'Balance Sheet'!D43 -> 0.42683127
A20: Debt-to-Assets | B20: =('Balance Sheet'!B29+'Balance Sheet'!B34)/'Balance Sheet'!B23 -> 0.32038275 | C20: =('Balance Sheet'!C29+'Balance Sheet'!C34)/'Balance Sheet'!C23 -> 0.28491188 | D20: =('Balance Sheet'!D29+'Balance Sheet'!D34)/'Balance Sheet'!D23 -> 0.25263813
A21: Interest Coverage (EBIT / Interest Expense) | B21: ='Income Statement'!B23/ABS('Income Statement'!B26) -> 9 | C21: ='Income Statement'!C23/ABS('Income Statement'!C26) -> 9 | D21: ='Income Statement'!D23/ABS('Income Statement'!D26) -> 9
A23: Efficiency Ratios
A24: Asset Turnover | B24: ='Income Statement'!B9/'Balance Sheet'!B23 -> 1.0946411 | C24: ='Income Statement'!C9/'Balance Sheet'!C23 -> 1.042981 | D24: ='Income Statement'!D9/'Balance Sheet'!D23 -> 0.99597722
A25: Days Sales Outstanding (AR Days) | B25: ='Balance Sheet'!B9/'Income Statement'!B9*365 -> 49.853659 | C25: ='Balance Sheet'!C9/'Income Statement'!C9*365 -> 49.853659 | D25: ='Balance Sheet'!D9/'Income Statement'!D9*365 -> 49.853659
A26: Days Inventory Outstanding | B26: ='Balance Sheet'!B10/'Income Statement'!B11*365 -> 95.595238 | C26: ='Balance Sheet'!C10/'Income Statement'!C11*365 -> 95.595238 | D26: ='Balance Sheet'!D10/'Income Statement'!D11*365 -> 95.595238
A27: Days Payable Outstanding | B27: ='Balance Sheet'!B27/'Income Statement'!B11*365 -> 78.214286 | C27: ='Balance Sheet'!C27/'Income Statement'!C11*365 -> 78.214286 | D27: ='Balance Sheet'!D27/'Income Statement'!D11*365 -> 78.214286
A29: Cash Flow Ratios
A30: Operating Cash Flow Margin | B30: ='Cash Flow Statement'!B14/'Income Statement'!B9 -> 0.12817561 | C30: ='Cash Flow Statement'!C14/'Income Statement'!C9 -> 0.12817561 | D30: ='Cash Flow Statement'!D14/'Income Statement'!D9 -> 0.12817561
A31: Free Cash Flow ($) | B31: ='Cash Flow Statement'!B14+'Cash Flow Statement'!B17 -> 813.8 | C31: ='Cash Flow Statement'!C14+'Cash Flow Statement'!C17 -> 813.8 | D31: ='Cash Flow Statement'!D14+'Cash Flow Statement'!D17 -> 813.8
A32: Free Cash Flow Margin | B32: =B31/'Income Statement'!B9 -> 0.079395122 | C32: =C31/'Income Statement'!C9 -> 0.079395122 | D32: =D31/'Income Statement'!D9 -> 0.079395122
A33: Cash Conversion (CFO / Net Income) | B33: ='Cash Flow Statement'!B14/'Income Statement'!B34 -> 1.3631459 | C33: ='Cash Flow Statement'!C14/'Income Statement'!C34 -> 1.3631459 | D33: ='Cash Flow Statement'!D14/'Income Statement'!D34 -> 1.3631459
