Workbook

Sheet Project Summary
B2: GENERAL CONTRACTOR MASTER JOB ESTIMATE
B4: Project Name: | C4: Commercial Office Buildout
B5: Client Name: | C5: Apex Holdings LLC
B6: Project Location: | C6: 100 Corporate Parkway
B7: Estimator: | C7: J. Construction Manager
B9: Trade Worksheet Division | C9: Labor Cost Subtotal | D9: Material Cost Subtotal | E9: Subcontractor Cost Subtotal | F9: Total Direct Trade Cost
B10: Demolition & Site Work | C10: ='Demolition & Site Work'!F10 -> 11970 | D10: ='Demolition & Site Work'!H10 -> 1500 | E10: ='Demolition & Site Work'!J10 -> 16425 | F10: =SUM(C10:E10) -> 29895
B11: Concrete & Masonry | C11: ='Concrete & Masonry'!F10 -> 17400 | D11: ='Concrete & Masonry'!H10 -> 20435 | E11: ='Concrete & Masonry'!J10 -> 7775 | F11: =SUM(C11:E11) -> 45610
B12: Framing & Structural | C12: ='Framing & Structural'!F10 -> 13300 | D12: ='Framing & Structural'!H10 -> 33210 | E12: ='Framing & Structural'!J10 -> 4320 | F12: =SUM(C12:E12) -> 50830
B13: Roofing & Siding | C13: ='Roofing & Siding'!F10 -> 15980 | D13: ='Roofing & Siding'!H10 -> 19475 | E13: ='Roofing & Siding'!J10 -> 0 | F13: =SUM(C13:E13) -> 35455
B14: Doors & Windows | C14: ='Doors & Windows'!F10 -> 3320 | D14: ='Doors & Windows'!H10 -> 14800 | E14: ='Doors & Windows'!J10 -> 0 | F14: =SUM(C14:E14) -> 18120
B15: Drywall & Finishes | C15: ='Drywall & Finishes'!F10 -> 35865 | D15: ='Drywall & Finishes'!H10 -> 23695 | E15: ='Drywall & Finishes'!J10 -> 0 | F15: =SUM(C15:E15) -> 59560
B16: Plumbing System | C16: ='Plumbing System'!F10 -> 0 | D16: ='Plumbing System'!H10 -> 0 | E16: ='Plumbing System'!J10 -> 18670 | F16: =SUM(C16:E16) -> 18670
B17: HVAC System | C17: ='HVAC System'!F10 -> 0 | D17: ='HVAC System'!H10 -> 0 | E17: ='HVAC System'!J10 -> 29250 | F17: =SUM(C17:E17) -> 29250
B18: Electrical System | C18: ='Electrical System'!F10 -> 0 | D18: ='Electrical System'!H10 -> 0 | E18: ='Electrical System'!J10 -> 22565 | F18: =SUM(C18:E18) -> 22565
B19: TOTAL DIRECT FIELD COSTS | C19: =SUM(C10:C18) -> 97835 | D19: =SUM(D10:D18) -> 113115 | E19: =SUM(E10:E18) -> 99005 | F19: =SUM(F10:F18) -> 309955
B21: FINANCIAL MARKUPS & BUFFER ENGINE
B22: Project Contingency Buffer | E22: 0.05 | F22: =F19*E22 -> 15497.75
B23: Company Overhead & Administrative | E23: 0.1 | F23: =F19*E23 -> 30995.5
B24: Target Professional Net Profit Margin | E24: 0.08 | F24: =F19*E24 -> 24796.4
B26: GRAND TOTAL CONTRACT BID PRICE | F26: =F19+SUM(F22:F24) -> 381244.65
B29: STANDARD SCOPE EXCLUSIONS & CLIENT TERMS
B30: 1. This estimate is strictly valid for a maximum of 30 calendar days from the date of issuance due to market material volatility.
B31: 2. Scope Excludes: Hazardous material remediation (asbestos, lead), engineering plan fees, municipal permit acquisition costs, and hidden structural decay discovery.
B32: 3. Progress Payments: Standard billing structure applies (10% Mobilization Deposit, monthly progress draws against verified completion sheets, 5% Retainage release).

Sheet Demolition & Site Work
B2: DEMOLITION & SITE WORK COST WORKSHEET
B4: Description | C4: Unit | D4: Quantity | E4: Labor Unit | F4: Labor Total | G4: Material Unit | H4: Material Total | I4: Subcontract Unit/Cost | J4: Subcontract Total | K4: Line Total
B5: Structural Teardown | C5: SqFt | D5: 2500 | E5: 4.5 | F5: =D5*E5 -> 11250 | G5: 0 | H5: =D5*G5 -> 0 | I5: 0 | J5: =D5*I5 -> 0 | K5: =F5+H5+J5 -> 11250
B6: Tree Removal & Land Clearing | C6: Acre | D6: 1.5 | E6: 0 | F6: =D6*E6 -> 0 | G6: 0 | H6: =D6*G6 -> 0 | I6: 4500 | J6: =D6*I6 -> 6750 | K6: =F6+H6+J6 -> 6750
B7: Excavation & Earth Moving | C7: CuYd | D7: 450 | E7: 0 | F7: =D7*E7 -> 0 | G7: 0 | H7: =D7*G7 -> 0 | I7: 12 | J7: =D7*I7 -> 5400 | K7: =F7+H7+J7 -> 5400
B8: Erosion Control & Silt Fencing | C8: LinFt | D8: 600 | E8: 1.2 | F8: =D8*E8 -> 720 | G8: 2.5 | H8: =D8*G8 -> 1500 | I8: 0 | J8: =D8*I8 -> 0 | K8: =F8+H8+J8 -> 2220
B9: Debris Hauling & Dumpster Fees | C9: Tons | D9: 45 | E9: 0 | F9: =D9*E9 -> 0 | G9: 0 | H9: =D9*G9 -> 0 | I9: 95 | J9: =D9*I9 -> 4275 | K9: =F9+H9+J9 -> 4275
B10: Total Demolition & Site Work | F10: =SUM(F5:F9) -> 11970 | H10: =SUM(H5:H9) -> 1500 | J10: =SUM(J5:J9) -> 16425 | K10: =SUM(K5:K9) -> 29895

Sheet Concrete & Masonry
B2: CONCRETE & MASONRY COST WORKSHEET
B4: Description | C4: Unit | D4: Quantity | E4: Labor Unit | F4: Labor Total | G4: Material Unit | H4: Material Total | I4: Subcontract Unit/Cost | J4: Subcontract Total | K4: Line Total
B5: Foundation Footing Concrete | C5: CuYd | D5: 85 | E5: 0 | F5: =D5*E5 -> 0 | G5: 135 | H5: =D5*G5 -> 11475 | I5: 45 | J5: =D5*I5 -> 3825 | K5: =F5+H5+J5 -> 15300
B6: Slab Pouring Labor | C6: SqFt | D6: 3200 | E6: 3.75 | F6: =D6*E6 -> 12000 | G6: 0 | H6: =D6*G6 -> 0 | I6: 0 | J6: =D6*I6 -> 0 | K6: =F6+H6+J6 -> 12000
B7: Steel Rebar Reinforcement | C7: Tons | D7: 4 | E7: 0 | F7: =D7*E7 -> 0 | G7: 1100 | H7: =D7*G7 -> 4400 | I7: 350 | J7: =D7*I7 -> 1400 | K7: =F7+H7+J7 -> 5800
B8: CMU Retaining Wall Block | C8: Count | D8: 1200 | E8: 4.5 | F8: =D8*E8 -> 5400 | G8: 3.8 | H8: =D8*G8 -> 4560 | I8: 0 | J8: =D8*I8 -> 0 | K8: =F8+H8+J8 -> 9960
B9: Concrete Pumping Equipment Rental | C9: Days | D9: 3 | E9: 0 | F9: =D9*E9 -> 0 | G9: 0 | H9: =D9*G9 -> 0 | I9: 850 | J9: =D9*I9 -> 2550 | K9: =F9+H9+J9 -> 2550
B10: Total Concrete & Masonry | F10: =SUM(F5:F9) -> 17400 | H10: =SUM(H5:H9) -> 20435 | J10: =SUM(J5:J9) -> 7775 | K10: =SUM(K5:K9) -> 45610

Sheet Framing & Structural
B2: FRAMING & STRUCTURAL COST WORKSHEET
B4: Description | C4: Unit | D4: Quantity | E4: Labor Unit | F4: Labor Total | G4: Material Unit | H4: Material Total | I4: Subcontract Unit/Cost | J4: Subcontract Total | K4: Line Total
B5: Wood Exterior Stud Wall Framing | C5: LinFt | D5: 420 | E5: 14 | F5: =D5*E5 -> 5880 | G5: 18.5 | H5: =D5*G5 -> 7770 | I5: 0 | J5: =D5*I5 -> 0 | K5: =F5+H5+J5 -> 13650
B6: Interior Partition Framing | C6: LinFt | D6: 680 | E6: 9.5 | F6: =D6*E6 -> 6460 | G6: 11 | H6: =D6*G6 -> 7480 | I6: 0 | J6: =D6*I6 -> 0 | K6: =F6+H6+J6 -> 13940
B7: CDX Plywood Floor Sheathing | C7: Sheets | D7: 120 | E7: 8 | F7: =D7*E7 -> 960 | G7: 34 | H7: =D7*G7 -> 4080 | I7: 0 | J7: =D7*I7 -> 0 | K7: =F7+H7+J7 -> 5040
B8: Engineered Roof Trusses | C8: Count | D8: 48 | E8: 0 | F8: =D8*E8 -> 0 | G8: 185 | H8: =D8*G8 -> 8880 | I8: 40 | J8: =D8*I8 -> 1920 | K8: =F8+H8+J8 -> 10800
B9: Structural Steel I-Beams | C9: Count | D9: 4 | E9: 0 | F9: =D9*E9 -> 0 | G9: 1250 | H9: =D9*G9 -> 5000 | I9: 600 | J9: =D9*I9 -> 2400 | K9: =F9+H9+J9 -> 7400
B10: Total Framing & Structural | F10: =SUM(F5:F9) -> 13300 | H10: =SUM(H5:H9) -> 33210 | J10: =SUM(J5:J9) -> 4320 | K10: =SUM(K5:K9) -> 50830

Sheet Roofing & Siding
B2: ROOFING & SIDING COST WORKSHEET
B4: Description | C4: Unit | D4: Quantity | E4: Labor Unit | F4: Labor Total | G4: Material Unit | H4: Material Total | I4: Subcontract Unit/Cost | J4: Subcontract Total | K4: Line Total
B5: Architectural Asphalt Shingles | C5: Squares | D5: 38 | E5: 75 | F5: =D5*E5 -> 2850 | G5: 145 | H5: =D5*G5 -> 5510 | I5: 0 | J5: =D5*I5 -> 0 | K5: =F5+H5+J5 -> 8360
B6: Synthetic Roof Underlayment | C6: Rolls | D6: 9 | E6: 20 | F6: =D6*E6 -> 180 | G6: 85 | H6: =D6*G6 -> 765 | I6: 0 | J6: =D6*I6 -> 0 | K6: =F6+H6+J6 -> 945
B7: Aluminum Seamless Gutters | C7: LinFt | D7: 240 | E7: 4 | F7: =D7*E7 -> 960 | G7: 5.5 | H7: =D7*G7 -> 1320 | I7: 0 | J7: =D7*I7 -> 0 | K7: =F7+H7+J7 -> 2280
B8: Fiber Cement Siding Installation | C8: SqFt | D8: 2800 | E8: 4.25 | F8: =D8*E8 -> 11900 | G8: 3.9 | H8: =D8*G8 -> 10920 | I8: 0 | J8: =D8*I8 -> 0 | K8: =F8+H8+J8 -> 22820
B9: Housewrap Moisture Barrier | C9: Rolls | D9: 6 | E9: 15 | F9: =D9*E9 -> 90 | G9: 160 | H9: =D9*G9 -> 960 | I9: 0 | J9: =D9*I9 -> 0 | K9: =F9+H9+J9 -> 1050
B10: Total Roofing & Siding | F10: =SUM(F5:F9) -> 15980 | H10: =SUM(H5:H9) -> 19475 | J10: =SUM(J5:J9) -> 0 | K10: =SUM(K5:K9) -> 35455

Sheet Doors & Windows
B2: DOORS & WINDOWS COST WORKSHEET
B4: Description | C4: Unit | D4: Quantity | E4: Labor Unit | F4: Labor Total | G4: Material Unit | H4: Material Total | I4: Subcontract Unit/Cost | J4: Subcontract Total | K4: Line Total
B5: Vinyl Double-Hung Windows | C5: Count | D5: 24 | E5: 65 | F5: =D5*E5 -> 1560 | G5: 320 | H5: =D5*G5 -> 7680 | I5: 0 | J5: =D5*I5 -> 0 | K5: =F5+H5+J5 -> 9240
B6: Exterior Insulated Fiberglass Doors | C6: Count | D6: 3 | E6: 150 | F6: =D6*E6 -> 450 | G6: 650 | H6: =D6*G6 -> 1950 | I6: 0 | J6: =D6*I6 -> 0 | K6: =F6+H6+J6 -> 2400
B7: Interior Pre-Hung Hollow Core Doors | C7: Count | D7: 18 | E7: 45 | F7: =D7*E7 -> 810 | G7: 140 | H7: =D7*G7 -> 2520 | I7: 0 | J7: =D7*I7 -> 0 | K7: =F7+H7+J7 -> 3330
B8: Sliding Glass Patio Doors | C8: Count | D8: 2 | E8: 250 | F8: =D8*E8 -> 500 | G8: 1100 | H8: =D8*G8 -> 2200 | I8: 0 | J8: =D8*I8 -> 0 | K8: =F8+H8+J8 -> 2700
B9: Commercial Hardware & Locksets | C9: Lots | D9: 1 | E9: 0 | F9: =D9*E9 -> 0 | G9: 450 | H9: =D9*G9 -> 450 | I9: 0 | J9: =D9*I9 -> 0 | K9: =F9+H9+J9 -> 450
B10: Total Doors & Windows | F10: =SUM(F5:F9) -> 3320 | H10: =SUM(H5:H9) -> 14800 | J10: =SUM(J5:J9) -> 0 | K10: =SUM(K5:K9) -> 18120

Sheet Drywall & Finishes
B2: DRYWALL & FINISHES COST WORKSHEET
B4: Description | C4: Unit | D4: Quantity | E4: Labor Unit | F4: Labor Total | G4: Material Unit | H4: Material Total | I4: Subcontract Unit/Cost | J4: Subcontract Total | K4: Line Total
B5: Drywall Hanging (5/8-inch Boards) | C5: Sheets | D5: 220 | E5: 18 | F5: =D5*E5 -> 3960 | G5: 16.5 | H5: =D5*G5 -> 3630 | I5: 0 | J5: =D5*I5 -> 0 | K5: =F5+H5+J5 -> 7590
B6: Tape, Mud, & Sand Smooth Finish | C6: SqFt | D6: 7200 | E6: 1.15 | F6: =D6*E6 -> 8280 | G6: 0.2 | H6: =D6*G6 -> 1440 | I6: 0 | J6: =D6*I6 -> 0 | K6: =F6+H6+J6 -> 9720
B7: Interior Premium Latex Painting | C7: SqFt | D7: 6500 | E7: 1.8 | F7: =D7*E7 -> 11700 | G7: 0.65 | H7: =D7*G7 -> 4225 | I7: 0 | J7: =D7*I7 -> 0 | K7: =F7+H7+J7 -> 15925
B8: Engineered Hardwood Floor Laying | C8: SqFt | D8: 1800 | E8: 4.5 | F8: =D8*E8 -> 8100 | G8: 6.75 | H8: =D8*G8 -> 12150 | I8: 0 | J8: =D8*I8 -> 0 | K8: =F8+H8+J8 -> 20250
B9: Porcelain Tile Flooring | C9: SqFt | D9: 450 | E9: 8.5 | F9: =D9*E9 -> 3825 | G9: 5 | H9: =D9*G9 -> 2250 | I9: 0 | J9: =D9*I9 -> 0 | K9: =F9+H9+J9 -> 6075
B10: Total Drywall & Finishes | F10: =SUM(F5:F9) -> 35865 | H10: =SUM(H5:H9) -> 23695 | J10: =SUM(J5:J9) -> 0 | K10: =SUM(K5:K9) -> 59560

Sheet Plumbing System
B2: PLUMBING SYSTEM COST WORKSHEET
B4: Description | C4: Unit | D4: Quantity | E4: Labor Unit | F4: Labor Total | G4: Material Unit | H4: Material Total | I4: Subcontract Unit/Cost | J4: Subcontract Total | K4: Line Total
B5: Rough-In PEX Supply & PVC Waste Lines | C5: Fixture | D5: 14 | E5: 0 | F5: =D5*E5 -> 0 | G5: 0 | H5: =D5*G5 -> 0 | I5: 650 | J5: =D5*I5 -> 9100 | K5: =F5+H5+J5 -> 9100
B6: Main Water Service Hookup | C6: Lot | D6: 1 | E6: 0 | F6: =D6*E6 -> 0 | G6: 0 | H6: =D6*G6 -> 0 | I6: 2400 | J6: =D6*I6 -> 2400 | K6: =F6+H6+J6 -> 2400
B7: Tankless Gas Water Heater Install | C7: Count | D7: 1 | E7: 0 | F7: =D7*E7 -> 0 | G7: 0 | H7: =D7*G7 -> 0 | I7: 3200 | J7: =D7*I7 -> 3200 | K7: =F7+H7+J7 -> 3200
B8: Bathroom & Kitchen Fixture Trims | C8: Fixture | D8: 14 | E8: 0 | F8: =D8*E8 -> 0 | G8: 0 | H8: =D8*G8 -> 0 | I8: 180 | J8: =D8*I8 -> 2520 | K8: =F8+H8+J8 -> 2520
B9: Sewage Ejector Pump System | C9: Lot | D9: 1 | E9: 0 | F9: =D9*E9 -> 0 | G9: 0 | H9: =D9*G9 -> 0 | I9: 1450 | J9: =D9*I9 -> 1450 | K9: =F9+H9+J9 -> 1450
B10: Total Plumbing System | F10: =SUM(F5:F9) -> 0 | H10: =SUM(H5:H9) -> 0 | J10: =SUM(J5:J9) -> 18670 | K10: =SUM(K5:K9) -> 18670

Sheet HVAC System
B2: HVAC SYSTEM COST WORKSHEET
B4: Description | C4: Unit | D4: Quantity | E4: Labor Unit | F4: Labor Total | G4: Material Unit | H4: Material Total | I4: Subcontract Unit/Cost | J4: Subcontract Total | K4: Line Total
B5: Complete Ductwork Layout & Fitting | C5: SqFt | D5: 3200 | E5: 0 | F5: =D5*E5 -> 0 | G5: 0 | H5: =D5*G5 -> 0 | I5: 3.8 | J5: =D5*I5 -> 12160 | K5: =F5+H5+J5 -> 12160
B6: 16 SEER Heat Pump & Air Handler | C6: Count | D6: 2 | E6: 0 | F6: =D6*E6 -> 0 | G6: 0 | H6: =D6*G6 -> 0 | I6: 6800 | J6: =D6*I6 -> 13600 | K6: =F6+H6+J6 -> 13600
B7: Digital Smart Thermostats | C7: Count | D7: 2 | E7: 0 | F7: =D7*E7 -> 0 | G7: 0 | H7: =D7*G7 -> 0 | I7: 250 | J7: =D7*I7 -> 500 | K7: =F7+H7+J7 -> 500
B8: Gas Piping & Venting Run | C8: LinFt | D8: 80 | E8: 0 | F8: =D8*E8 -> 0 | G8: 0 | H8: =D8*G8 -> 0 | I8: 28 | J8: =D8*I8 -> 2240 | K8: =F8+H8+J8 -> 2240
B9: System Balancing & Certification | C9: Lot | D9: 1 | E9: 0 | F9: =D9*E9 -> 0 | G9: 0 | H9: =D9*G9 -> 0 | I9: 750 | J9: =D9*I9 -> 750 | K9: =F9+H9+J9 -> 750
B10: Total HVAC System | F10: =SUM(F5:F9) -> 0 | H10: =SUM(H5:H9) -> 0 | J10: =SUM(J5:J9) -> 29250 | K10: =SUM(K5:K9) -> 29250

Sheet Electrical System
B2: ELECTRICAL SYSTEM COST WORKSHEET
B4: Description | C4: Unit | D4: Quantity | E4: Labor Unit | F4: Labor Total | G4: Material Unit | H4: Material Total | I4: Subcontract Unit/Cost | J4: Subcontract Total | K4: Line Total
B5: 200-Amp Main Service Panel & Breakers | C5: Lot | D5: 1 | E5: 0 | F5: =D5*E5 -> 0 | G5: 0 | H5: =D5*G5 -> 0 | I5: 2800 | J5: =D5*I5 -> 2800 | K5: =F5+H5+J5 -> 2800
B6: Whole-House Rough-In Wiring Romex | C6: SqFt | D6: 3200 | E6: 0 | F6: =D6*E6 -> 0 | G6: 0 | H6: =D6*G6 -> 0 | I6: 4.25 | J6: =D6*I6 -> 13600 | K6: =F6+H6+J6 -> 13600
B7: Recessed LED Can Light Fixtures | C7: Count | D7: 45 | E7: 0 | F7: =D7*E7 -> 0 | G7: 0 | H7: =D7*G7 -> 0 | I7: 85 | J7: =D7*I7 -> 3825 | K7: =F7+H7+J7 -> 3825
B8: GFI Outlets & Standard Switches | C8: Lot | D8: 1 | E8: 0 | F8: =D8*E8 -> 0 | G8: 0 | H8: =D8*G8 -> 0 | I8: 1200 | J8: =D8*I8 -> 1200 | K8: =F8+H8+J8 -> 1200
B9: Low-Voltage Cat6 Data Network | C9: Drops | D9: 12 | E9: 0 | F9: =D9*E9 -> 0 | G9: 0 | H9: =D9*G9 -> 0 | I9: 95 | J9: =D9*I9 -> 1140 | K9: =F9+H9+J9 -> 1140
B10: Total Electrical System | F10: =SUM(F5:F9) -> 0 | H10: =SUM(H5:H9) -> 0 | J10: =SUM(J5:J9) -> 22565 | K10: =SUM(K5:K9) -> 22565
